Hyperion-0.9.11.dist-info/LICENSE
Hyperion-0.9.11.dist-info/zip-safe
Hyperion-0.9.11.dist-info/METADATA
Hyperion-0.9.11.dist-info/RECORD
Hyperion-0.9.11.dist-info/top_level.txt
Hyperion-0.9.11.dist-info/entry_points.txt
Hyperion-0.9.11.dist-info/WHEEL
Hyperion-0.9.11.data/scripts/hyperion2fits
Hyperion-0.9.11.data/scripts/hyperion
hyperion/version.py
hyperion/__init__.py
hyperion/_version.py
hyperion/conftest.py
hyperion/conf/conf_files.py
hyperion/conf/__init__.py
hyperion/conf/tests/test_peeled_image_conf.py
hyperion/conf/tests/test_image_conf.py
hyperion/conf/tests/test_run_conf.py
hyperion/conf/tests/test_conf_io.py
hyperion/conf/tests/__init__.py
hyperion/dust/dust_type.py
hyperion/dust/optical_properties.py
hyperion/dust/emissivities.py
hyperion/dust/__init__.py
hyperion/dust/mean_opacities.py
hyperion/dust/tests/__init__.py
hyperion/dust/tests/test_mean_opacities.py
hyperion/dust/tests/test_dust.py
hyperion/dust/tests/test_optical_properties.py
hyperion/dust/tests/test_emissivities.py
hyperion/util/polyhedra.py
hyperion/util/convenience.py
hyperion/util/constants.py
hyperion/util/meshgrid.py
hyperion/util/_integrate_core.abi3.so
hyperion/util/_interpolate_core.abi3.so
hyperion/util/functions.py
hyperion/util/otf_hdf5.py
hyperion/util/validator.py
hyperion/util/__init__.py
hyperion/util/parfile.py
hyperion/util/interpolate.py
hyperion/util/integrate.py
hyperion/util/nans.py
hyperion/util/tests/test_functions.py
hyperion/util/tests/test_interpolate.py
hyperion/util/tests/test_integrate.py
hyperion/util/tests/__init__.py
hyperion/sources/source.py
hyperion/sources/__init__.py
hyperion/sources/tests/test_source.py
hyperion/sources/tests/__init__.py
hyperion/sources/tests/test_source_io.py
hyperion/densities/power_law_envelope.py
hyperion/densities/core.py
hyperion/densities/__init__.py
hyperion/densities/ambient_medium.py
hyperion/densities/flared_disk.py
hyperion/densities/alpha_disk.py
hyperion/densities/ulrich_envelope.py
hyperion/densities/bipolar_cavity.py
hyperion/densities/tests/__init__.py
hyperion/densities/tests/test_densities.py
hyperion/grid/amr_grid.py
hyperion/grid/yt3_wrappers.py
hyperion/grid/spherical_polar_grid.py
