Metadata-Version: 2.1
Name: Hyperion
Version: 0.9.11
Summary: Monte-Carlo Radiative Transfer Code
Home-page: http://www.hyperion-rt.org
Author: Thomas Robitaille
Author-email: thomas.robitaille@gmail.com
License: BSD
Requires-Python: >=3.9
License-File: LICENSE
Requires-Dist: numpy>=1.11
Requires-Dist: matplotlib>=1.5
Requires-Dist: astropy>=1.2
Requires-Dist: h5py>=2.4
Requires-Dist: decorator
Provides-Extra: recommended
Requires-Dist: yt>=3.2; extra == "recommended"
Provides-Extra: docs
Requires-Dist: sphinx; extra == "docs"
Requires-Dist: numpydoc; extra == "docs"
Provides-Extra: test
Requires-Dist: pytest; extra == "test"
